command_add/__init__.py
command_add-0.2.0.dist-info/METADATA
command_add-0.2.0.dist-info/WHEEL
command_add-0.2.0.dist-info/entry_points.txt
command_add-0.2.0.dist-info/RECORD
